sentimentpl/__init__.py
sentimentpl/datautils.py
sentimentpl/models.py
sentimentpl/train.py
sentimentpl/trained_models/__init__.py
sentimentpl/trained_models/latest.pth
sentimentpl-0.0.6.dist-info/LICENSE
sentimentpl-0.0.6.dist-info/METADATA
sentimentpl-0.0.6.dist-info/WHEEL
sentimentpl-0.0.6.dist-info/top_level.txt
sentimentpl-0.0.6.dist-info/RECORD
