Metadata-Version: 2.1
Name: sentimentpl
Version: 0.0.6
Summary: PyTorch models for polish language sentiment regression based on allegro/herbert and CLARIN-PL dataset
Home-page: https://github.com/philvec/sentimentPL
Author: Filip Strzałka
Author-email: strzalkafilip@gmail.com
License: UNKNOWN
Platform: UNKNOWN
Classifier: Programming Language :: Python :: 3
Classifier: License :: OSI Approved :: GNU General Public License v3 (GPLv3)
Classifier: Operating System :: OS Independent
Requires-Python: >=3.7
Requires-Dist: torch (>=1.7.1)
Requires-Dist: transformers
Requires-Dist: tqdm
Requires-Dist: matplotlib
